pydbussend/__init__.py
pydbussend/__version__.py
pydbussend-2024.12.24.dist-info/METADATA
pydbussend-2024.12.24.dist-info/WHEEL
pydbussend-2024.12.24.dist-info/licenses/LICENSE
pydbussend-2024.12.24.dist-info/RECORD
