Metadata-Version: 2.1
Name: pydbussend
Version: 2024.12.24
Author-email: mikigo <huangmingqiang@uniontech.com>
License: GPL2.0
License-File: LICENSE
Requires-Python: >=3.6
Requires-Dist: funnylog2
Requires-Dist: nocmd
